nonebot_plugin_youthstudy/__init__.py
nonebot_plugin_youthstudy/convert_pic.py
nonebot_plugin_youthstudy/dao/__init__.py
nonebot_plugin_youthstudy/dao/group_dao.py
nonebot_plugin_youthstudy/dao/user_dao.py
nonebot_plugin_youthstudy/file_tool.py
nonebot_plugin_youthstudy/get_src.py
nonebot_plugin_youthstudy/getdata.py
nonebot_plugin_youthstudy/resource/bac/bac-1.png
nonebot_plugin_youthstudy/resource/bac/bac.png
nonebot_plugin_youthstudy/resource/bac/图层 1.png
nonebot_plugin_youthstudy/resource/bac/图层2.png
nonebot_plugin_youthstudy/resource/font/font.otf
nonebot_plugin_youthstudy/utils.py
nonebot_plugin_youthstudy-1.1.8.dist-info/LICENSE
nonebot_plugin_youthstudy-1.1.8.dist-info/METADATA
nonebot_plugin_youthstudy-1.1.8.dist-info/WHEEL
nonebot_plugin_youthstudy-1.1.8.dist-info/RECORD
