Metadata-Version: 2.1
Name: nonebot-plugin-youthstudy
Version: 1.1.8
Summary: 基于nonebot2的青年大学习插件
Home-page: https://github.com/ayanamiblhx/nonebot_plugin_youthstudy
License: GNU General Public License v3.0
Author: ayanamiblhx
Author-email: 1196818079@qq.com
Requires-Python: >=3.8,<4.0
Classifier: License :: Other/Proprietary License
Classifier: Programming Language :: Python :: 3
Classifier: Programming Language :: Python :: 3.8
Classifier: Programming Language :: Python :: 3.9
Classifier: Programming Language :: Python :: 3.10
Classifier: Programming Language :: Python :: 3.11
Requires-Dist: Pillow (>=9.0.1,<10.0.0)
Requires-Dist: beautifulsoup4 (>=4.10.0,<5.0.0)
Requires-Dist: httpx (>=0.23.0,<0.24.0)
Requires-Dist: lxml (>=4.7,<5.0)
Requires-Dist: nonebot-adapter-onebot (>=2.0.0b1,<3.0.0)
Requires-Dist: nonebot-plugin-apscheduler (>=0.2.0,<0.3.0)
Requires-Dist: nonebot2 (>=2.0.0b2)
